{"app_id":"097332a388c2","data":{"biz_data":{"data":{"face_list":[{"best_quality":0.6837846040725708,"loc":"592,241,742,439","person_id":"b272a28b-a838-48a0-8fb8-017d6afba255"},{"best_quality":0.52427941560745239,"loc":"1137,391,1293,583","person_id":"f3575c93-7bca-423a-ab41-eee8b8109017"}],"plate_code":"test_XY667814","position":"1,4","sensors":[{"adc":32884.69921875,"sensor_id":0,"weight":128.93539428710938},{"adc":31971.94921875,"sensor_id":1,"weight":232.83430480957031}],"total_weight":362,"weight_change":-120},"end_time":1569645726329,"start_time":1569645725829,"timestamp":1569645726379,"type":"PICK","unit_code":"test_733203be-9e4b-11e9-a23e-00163e0ae160"}},"request_id":"1dd316d0-4960-459e-ae16-cb1b6873","router":"/commodity/external/CUSTOMER_MESSAGE/v1.0","uid":"uid_7fc78d24","version":"1.0"}