{"app_id":"097332a388c2","data":{"biz_data":{"data":{"face_list":[{"loc":"826,896,1018,1112","person_id":"fe6db256-f551-441f-9a72-bf531cdf1bbb"}],"plate_code":"test_XY667817","position":"1,7","sensors":[{"adc":29799.416015625,"sensor_id":0,"weight":573.8062744140625},{"adc":1022.25,"sensor_id":1,"weight":129.51959228515625}],"total_weight":703,"weight_change":-329},"end_time":1566370742904,"start_time":1566370742404,"timestamp":1566370742954,"type":"PICK","unit_code":"test_733203be-9e4b-11e9-a23e-00163e0ae160"}},"request_id":"a258728f-cc91-470e-882d-427a61a1","router":"/commodity/external/CUSTOMER_MESSAGE/v1.0","uid":"uid_7fc78d24","version":"1.0"}