{"app_id":"097332a388c2","data":{"biz_data":{"data":{"face_list":[{"best_quality":0.0,"loc":"1111,770,1297,974","person_id":"638057c1-eaef-4c83-b1e7-2825416eceb0"}],"plate_code":"test_XY667812","position":"1,2","sensors":[{"adc":31061.25,"sensor_id":0,"weight":244.33889770507812},{"adc":34465.0,"sensor_id":1,"weight":110.77080535888672}],"total_weight":355,"weight_change":-175},"end_time":1569644646457,"start_time":1569644645957,"timestamp":1569644646507,"type":"PICK","unit_code":"test_733203be-9e4b-11e9-a23e-00163e0ae160"}},"request_id":"34237f53-7ae6-4c4f-a1cb-dfc6c2a4","router":"/commodity/external/CUSTOMER_MESSAGE/v1.0","uid":"uid_7fc78d24","version":"1.0"}