{"app_id":"097332a388c2","data":{"biz_data":{"data":{"face_list":[{"loc":"1266,305,1386,473","person_id":"1fdd7aa3-e89e-4e71-997c-69c4631f7238"},{"loc":"644,237,794,429","person_id":"349b522f-e9d9-43c1-b5dc-39b51f8b0f45"}],"plate_code":"test_XY66781G","position":"4,2","sensors":[{"adc":31985.666015625,"sensor_id":0,"weight":168.25054931640625},{"adc":31245.416015625,"sensor_id":1,"weight":147.32315063476562}],"total_weight":316,"weight_change":-74},"end_time":1567069575586,"start_time":1567069575086,"timestamp":1567069575636,"type":"PICK","unit_code":"test_733203be-9e4b-11e9-a23e-00163e0ae160"}},"request_id":"d0de976d-e319-414c-82af-9e4857a7","router":"/commodity/external/CUSTOMER_MESSAGE/v1.0","uid":"uid_7fc78d24","version":"1.0"}